[{"id":"1758507178598486199","name":"李老师不是你老师","createdDate":"2024-02-16 23:02:37","content":"2月15日，家属继续在商场外维权，期间一位家属爬上警车车顶要跳车，被一旁的警察拦住 https://t.co/iIVtWrQ4Ia","images":"","videos":"/temp/video/2024/x-Month-2/j-Day-16/whyyoutouzhele/1758507178598486199_0.jpg,"},{"id":"1758502336681431059","name":"李老师不是你老师","createdDate":"2024-02-16 22:43:23","content":"2月15日，内蒙古自治区和林格尔县，内蒙古警察职业学院新校区建设项目拖欠工人工资，工人们聚集在警察职业学院外拉横幅讨薪。 https://t.co/x8FkQy4yah","images":"","videos":"/temp/video/2024/x-Month-2/j-Day-16/whyyoutouzhele/1758502336681431059_0.jpg,"},{"id":"1758500242712891399","name":"李老师不是你老师","createdDate":"2024-02-16 22:35:03","content":"网友补充 https://t.co/bUXWsSSEG4","images":"/temp/image/2024/x-Month-2/1758500242712891399_0.jpg,","videos":""},{"id":"1758494931339935921","name":"李老师不是你老师","createdDate":"2024-02-16 22:13:57","content":"关于全过程民主\n相较于雷主任的雾里看花\n或许中国人民的实际体验更有说服力\nhttps://t.co/qBQk5pfp6I","images":"","videos":""},{"id":"1758494279201112309","name":"李老师不是你老师","createdDate":"2024-02-16 22:11:22","content":"2月16日，媒体报道台湾中华妇女联合总会主任委员雷倩在台湾节目中赞叹大陆全过程民主，表示民主不是只有一人一票的普选，需要全世界仔细思考。\n 引发四万网友在评论区集体阴阳怪气。 https://t.co/93QSGK7Nxo","images":"","videos":"/temp/video/2024/x-Month-2/j-Day-16/whyyoutouzhele/1758494279201112309_0.jpg,"}]