[{"id":"1741955224716124228","name":"李老师不是你老师","createdDate":"2024-01-02 06:51:04","content":"@RonaldSimmonsUS 应该是不小心点到教师节的文件上去了","images":"","videos":""},{"id":"1741939923836342783","name":"李老师不是你老师","createdDate":"2024-01-02 05:50:16","content":"@zwang5893 ？","images":"","videos":""},{"id":"1741937285782704509","name":"李老师不是你老师","createdDate":"2024-01-02 05:39:47","content":"1月1日，郑州千玺广场跨年倒数发生乌龙，倒数到第八秒时，突然出现两句“老师！您好！”，然后整座建筑灯光突然熄灭。 https://t.co/UeY3Sch4SY","images":"","videos":"/temp/video/2024/y-Month-1/x-Day-02/whyyoutouzhele/1741937285782704509_0.jpg,"}]