[{"id":"1740522337341157618","name":"李老师不是你老师","createdDate":"2023-12-29 07:57:17","content":"目前，河南商丘网络电视台的直播间评论区\n民众向正在做报告的领导“要真相”\n感叹“天太黑了” https://t.co/NiQeqyeV8p","images":"","videos":"/temp/video/2023/n-Month-12/av-Day-29/whyyoutouzhele/1740522337341157618_0.jpg,"},{"id":"1740516914051559571","name":"李老师不是你老师","createdDate":"2023-12-29 07:35:44","content":"@stardiamond4050 乌鲁木齐之夜全城走上街头冲进师部，起因是当地社区干部扇了一个小孩一耳光。\n这一年来所有大型社会事件都是长期积攒的民怨恰好遇上了一个随机的宣泄口","images":"","videos":""},{"id":"1740493365655859284","name":"李老师不是你老师","createdDate":"2023-12-29 06:02:09","content":"一段宁陵县育华中学学生讲述事情经过的视频在29日凌晨被抖音网友们接力转发\n但请注意，该视频的内容为这名学生的个人主观描述，事件的具体原因目前还没有定论 https://t.co/SyqpVTxWUm","images":"","videos":"/temp/video/2023/n-Month-12/av-Day-29/whyyoutouzhele/1740493365655859284_0.jpg,"},{"id":"1740434316578951499","name":"李老师不是你老师","createdDate":"2023-12-29 02:07:31","content":"28日晚，宁陵县封路戒严画面 https://t.co/BbpKMiEBzw","images":"","videos":"/temp/video/2023/n-Month-12/av-Day-29/whyyoutouzhele/1740434316578951499_0.jpg,"},{"id":"1740433239951745302","name":"李老师不是你老师","createdDate":"2023-12-29 02:03:14","content":"当天下午，宁陵县县长出面与民众交涉\n民众要求“杀人偿命” https://t.co/qWbio7ZGMq","images":"","videos":"/temp/video/2023/n-Month-12/av-Day-29/whyyoutouzhele/1740433239951745302_0.jpg,"},{"id":"1740427959427887225","name":"李老师不是你老师","createdDate":"2023-12-29 01:42:15","content":"目前，商丘境内多条高速公路因大雾封闭 https://t.co/tFGWP6SS7c","images":"/temp/image/2023/n-Month-12/1740427959427887225_0.jpg,/temp/image/2023/n-Month-12/1740427959427887225_1.jpg,","videos":""},{"id":"1740422720574107665","name":"李老师不是你老师","createdDate":"2023-12-29 01:21:26","content":"目前网传消息称，28日晚，有宁陵县当地派出所在群里紧急通知民众，明天不准前往育华园中学。 https://t.co/Ni5gvWbKMV","images":"/temp/image/2023/n-Month-12/1740422720574107665_0.jpg,","videos":""},{"id":"1740411591836008866","name":"李老师不是你老师","createdDate":"2023-12-29 00:37:13","content":"截至目前，民众已经散去，学校周围布置了大量警力，封路警戒 https://t.co/biUAyByOWb","images":"","videos":"/temp/video/2023/n-Month-12/av-Day-29/whyyoutouzhele/1740411591836008866_0.jpg,"},{"id":"1740411149060018679","name":"李老师不是你老师","createdDate":"2023-12-29 00:35:27","content":"愤怒的民众把校领导的车放气刮花 https://t.co/DPDkG6Wk2b","images":"","videos":"/temp/video/2023/n-Month-12/av-Day-29/whyyoutouzhele/1740411149060018679_0.jpg,"},{"id":"1740410695341203614","name":"李老师不是你老师","createdDate":"2023-12-29 00:33:39","content":"校长被愤怒的民众殴打，民众要求他跪下 https://t.co/uR05ojwUIs","images":"","videos":"/temp/video/2023/n-Month-12/av-Day-29/whyyoutouzhele/1740410695341203614_0.jpg,"},{"id":"1740753196870742337","name":"李老师不是你老师","createdDate":"2023-12-29 23:14:38","content":"@nict570npc 你上街买过东西吗？😅\n来收摊位费的谁穿制服？你明天跟妈妈一起出门买次菜吧","images":"","videos":""},{"id":"1740749834968314346","name":"李老师不是你老师","createdDate":"2023-12-29 23:01:16","content":"其他银行员工补充 https://t.co/gDfVoEFEMK","images":"/temp/image/2023/n-Month-12/1740749834968314346_0.jpg,/temp/image/2023/n-Month-12/1740749834968314346_1.jpg,","videos":""},{"id":"1740744833440862435","name":"李老师不是你老师","createdDate":"2023-12-29 22:41:24","content":"根据女子描述，12月25日，公安机关在鉴定意见上明确说明，在其内穿衣物上检测到戴翔的DNA。\n但是当她前往纪委提供材料时，却遭纪委劝其“再等等”“先不要说出去”等。 https://t.co/hwUey1fuu3","images":"/temp/image/2023/n-Month-12/1740744833440862435_0.jpg,","videos":""},{"id":"1740744013395939632","name":"李老师不是你老师","createdDate":"2023-12-29 22:38:08","content":"12月29日，一名女子实名举报广西融资担保集团党委书记戴翔对自己强奸未遂。\n据其自述，11月18日，戴翔利用带她出差的机会在酒店意图强奸，在她的激烈反抗下未能得逞。\n事情发生后，虽然她向相关部门积极举报，但是仍没获得有效结局，现在她恳请网友为自己伸张正义。 https://t.co/zbrvH1kYGH","images":"","videos":"/temp/video/2023/n-Month-12/av-Day-29/whyyoutouzhele/1740744013395939632_0.jpg,"},{"id":"1740726435235713293","name":"李老师不是你老师","createdDate":"2023-12-29 21:28:17","content":"邯郸工商银行员工投稿 https://t.co/OjPFDiIWwq","images":"/temp/image/2023/n-Month-12/1740726435235713293_0.jpg,/temp/image/2023/n-Month-12/1740726435235713293_1.jpg,/temp/image/2023/n-Month-12/1740726435235713293_2.jpg,","videos":""},{"id":"1740723245559746783","name":"李老师不是你老师","createdDate":"2023-12-29 21:15:37","content":"当然，机构臃肿也是我们传统文化的一部分 https://t.co/fioh3CrniK","images":"/temp/image/2023/n-Month-12/1740723245559746783_0.jpg,/temp/image/2023/n-Month-12/1740723245559746783_1.jpg,","videos":""},{"id":"1740721276627353966","name":"李老师不是你老师","createdDate":"2023-12-29 21:07:48","content":"12月29日，媒体报道，武汉大学学生发布多个视频质疑称，在武汉大学书画协会举办的一场活动中，44名获奖人员全部都是按级别排列的协会干部或前干部。\n网友评价，仅仅一个大学的书画协会就设立了这么多学生干部，真是“人人有官做”。 https://t.co/u0Tf3iwhpz","images":"/temp/image/2023/n-Month-12/1740721276627353966_0.jpg,","videos":""},{"id":"1740718693251002776","name":"李老师不是你老师","createdDate":"2023-12-29 20:57:32","content":"12月29日，河南商丘。\n一名警察发布了一则警队训练的视频，结果评论区引来大量网友们疯狂嘲讽。\n最后不得不开启评论保护 https://t.co/UfsPY8YqHZ","images":"/temp/image/2023/n-Month-12/1740718693251002776_0.jpg,/temp/image/2023/n-Month-12/1740718693251002776_1.jpg,/temp/image/2023/n-Month-12/1740718693251002776_2.jpg,/temp/image/2023/n-Month-12/1740718693251002776_3.jpg,","videos":""},{"id":"1740718513281781859","name":"李老师不是你老师","createdDate":"2023-12-29 20:56:49","content":"12月28日，广东，数十位农名工坐在大厦楼顶边缘，拉横幅讨薪，楼下的消防员们则布置好了气垫。 https://t.co/IhO9ueXCAS","images":"","videos":"/temp/video/2023/n-Month-12/av-Day-29/whyyoutouzhele/1740718513281781859_0.jpg,"},{"id":"1740708696546811961","name":"李老师不是你老师","createdDate":"2023-12-29 20:17:48","content":"12月27日，北京。一位公交司机在社交平台发视频称，刚接到紧急通知，集团的工资总额从2800元改成了1420元，发放时间上级未公布。\n司机质疑，北京公交集团原党委书记董事长王春杰因违法违纪被调查后，司机们拿到的工资反而变少了，是不是新上任的官员又从司机身上扒皮了。 https://t.co/1yvA5CGjzb","images":"","videos":"/temp/video/2023/n-Month-12/av-Day-29/whyyoutouzhele/1740708696546811961_0.jpg,"},{"id":"1740707337831366991","name":"李老师不是你老师","createdDate":"2023-12-29 20:12:24","content":"@nict570npc 这种管理者欺压底层百姓的事情在中国很常见？\n你是50W在故意抹黑中国吧😅","images":"","videos":""},{"id":"1740706582415933747","name":"李老师不是你老师","createdDate":"2023-12-29 20:09:24","content":"12月29日，有网友发现，美食作家王刚疑似被“软封杀”\n测试王刚的全平台账号发现\n他的抖音显示无法关注；\n西瓜视频无法关注并且主页显示该用户已被禁言；\nB站目前可以关注；\n微博点击关注显示已关注，但是关注列表里并没有王刚。\n另外，自从“蛋炒饭风波”后，王刚再也没有发布过任何视频。 https://t.co/6vE83Wx0d8","images":"/temp/image/2023/n-Month-12/1740706582415933747_0.jpg,","videos":""},{"id":"1740705352453161009","name":"李老师不是你老师","createdDate":"2023-12-29 20:04:31","content":"@iamcunzhang 因为惯性。无论是食堂里吃出鼠头，还是村里拐卖妇女，亦或是学生跳楼\n如果认真督办，那么被伤害的就是自己在这个小地方的政治盟友或者利益集团，所以只要出了任何事必然都是以糊弄受害者+降低影响为主要路径…","images":"","videos":""},{"id":"1740698245678965105","name":"李老师不是你老师","createdDate":"2023-12-29 19:36:17","content":"12月29日，宁陵的每个路口都布置了大量特警\n关键路口用数量私家车横摆封路 https://t.co/0U4mMaFpZw","images":"","videos":"/temp/video/2023/n-Month-12/av-Day-29/whyyoutouzhele/1740698245678965105_0.jpg,"},{"id":"1740696285525725329","name":"李老师不是你老师","createdDate":"2023-12-29 19:28:29","content":"网友补充的械斗场面 https://t.co/ncwNWDkMru","images":"","videos":"/temp/video/2023/n-Month-12/av-Day-29/whyyoutouzhele/1740696285525725329_0.jpg,"},{"id":"1740695743525171578","name":"李老师不是你老师","createdDate":"2023-12-29 19:26:20","content":"12月29日，西安交通大学工地门口，员工讨薪 https://t.co/ruhrwNPIww","images":"/temp/image/2023/n-Month-12/1740695743525171578_0.jpg,","videos":""},{"id":"1740693953488572572","name":"李老师不是你老师","createdDate":"2023-12-29 19:19:13","content":"12月29日，浙江桐乡市，现场几百名业主在建设局维权，要求领导下来，领导拒绝露面 https://t.co/SDAnpndv1F","images":"","videos":"/temp/video/2023/n-Month-12/av-Day-29/whyyoutouzhele/1740693953488572572_0.jpg,"},{"id":"1740692928820093011","name":"李老师不是你老师","createdDate":"2023-12-29 19:15:09","content":"招商银行宣布向员工“逆向讨薪”\n12月28日晚，招商银行发布监事会决议公告称，为缓释各类经营和管理风险，向2876名员工追索扣回绩效薪酬总金额5824万元，人均“退薪”2.03万元，占招行全部员工比例超过2.5%。 https://t.co/JW0QxT1Yxi","images":"/temp/image/2023/n-Month-12/1740692928820093011_0.jpg,","videos":""},{"id":"1740690703561441448","name":"李老师不是你老师","createdDate":"2023-12-29 19:06:18","content":"12月29日，广东珠海一强拆现场，几名执法人员将户主强行从家中拖走开始拆家。\n看着自己耗费一生心血建立的家园即将被摧毁，男子扒着栏杆撕心裂肺地哀嚎痛哭。 https://t.co/TIL1Or5qbd","images":"","videos":"/temp/video/2023/n-Month-12/av-Day-29/whyyoutouzhele/1740690703561441448_0.jpg,"},{"id":"1740689863895372262","name":"李老师不是你老师","createdDate":"2023-12-29 19:02:58","content":"12月28日，广东。老人坐公交车拒付车费后殴打司机，一旁的阿姨劝说了几句也被老人殴打。一学生以为老人没钱想要帮付，谁知老人称有钱但是不给，并殴打了那名学生。 https://t.co/JXD1b9FyEL","images":"","videos":"/temp/video/2023/n-Month-12/av-Day-29/whyyoutouzhele/1740689863895372262_0.jpg,"},{"id":"1740689750682677533","name":"李老师不是你老师","createdDate":"2023-12-29 19:02:31","content":"12月28日，广东广州。地铁3号线，一老人为了让他人给自己让座，竟向座椅泼水逼走乘客。 https://t.co/e87XhH6RyT","images":"","videos":"/temp/video/2023/n-Month-12/av-Day-29/whyyoutouzhele/1740689750682677533_0.jpg,"},{"id":"1740689197735030902","name":"李老师不是你老师","createdDate":"2023-12-29 19:00:19","content":"12月28日，湖南郴州，湘永菜市场路边摊位一男子向摊贩收费时发生争执，随后一脚踢翻摊贩的菜。 https://t.co/RxTJ3fLwC3","images":"","videos":"/temp/video/2023/n-Month-12/av-Day-29/whyyoutouzhele/1740689197735030902_0.jpg,"},{"id":"1740688531927040014","name":"李老师不是你老师","createdDate":"2023-12-29 18:57:41","content":"12月28日半夜，山东潍坊。\n一群年轻人在街头发生冲突，双方互射烟花，手持砍刀钢管互殴。\n29日上午，警察对他们展开抓捕 https://t.co/rMuNgsk0se","images":"","videos":"/temp/video/2023/n-Month-12/av-Day-29/whyyoutouzhele/1740688531927040014_0.jpg,"},{"id":"1740687617585561685","name":"李老师不是你老师","createdDate":"2023-12-29 18:54:03","content":"网友们在评论区表达支持\n其中一名网友说自己的丈夫被警察带走了 https://t.co/zRa7h0eqib","images":"/temp/image/2023/n-Month-12/1740687617585561685_0.jpg,/temp/image/2023/n-Month-12/1740687617585561685_1.jpg,/temp/image/2023/n-Month-12/1740687617585561685_2.jpg,/temp/image/2023/n-Month-12/1740687617585561685_3.jpg,","videos":""},{"id":"1740686498629140508","name":"李老师不是你老师","createdDate":"2023-12-29 18:49:36","content":"12月29日清晨，宁陵县。事发第二天，整个县城被笼罩在大雾里，县城各个路口都有警察把守，即便如此，依旧还有人走上街头为坠亡学生发声。 https://t.co/0HZU7LT6eC","images":"","videos":"/temp/video/2023/n-Month-12/av-Day-29/whyyoutouzhele/1740686498629140508_0.jpg,"},{"id":"1740685564767273371","name":"李老师不是你老师","createdDate":"2023-12-29 18:45:53","content":"12月29日清晨，宁陵县多个路口依然处于封锁状态，并且路口仍然能看到警察和便衣驻守，并对每辆过往车辆进行盘查。 https://t.co/RVtoHv8UCP","images":"","videos":"/temp/video/2023/n-Month-12/av-Day-29/whyyoutouzhele/1740685564767273371_0.jpg,"}]